aws_sdk_bedrock_runtime/__init__.py
aws_sdk_bedrock_runtime/auth.py
aws_sdk_bedrock_runtime/client.py
aws_sdk_bedrock_runtime/config.py
aws_sdk_bedrock_runtime/deserialize.py
aws_sdk_bedrock_runtime/models.py
aws_sdk_bedrock_runtime/serialize.py
aws_sdk_bedrock_runtime/user_agent.py
aws_sdk_bedrock_runtime/_private/__init__.py
aws_sdk_bedrock_runtime/_private/schemas.py
aws_sdk_bedrock_runtime-0.1.0.dist-info/METADATA
aws_sdk_bedrock_runtime-0.1.0.dist-info/WHEEL
aws_sdk_bedrock_runtime-0.1.0.dist-info/licenses/LICENSE
aws_sdk_bedrock_runtime-0.1.0.dist-info/licenses/NOTICE
aws_sdk_bedrock_runtime-0.1.0.dist-info/RECORD
