Metadata-Version: 2.4
Name: aws_sdk_bedrock_runtime
Version: 0.1.0
Summary: aws_sdk_bedrock_runtime client
License: Apache-2.0
License-File: LICENSE
License-File: NOTICE
Keywords: aws_sdk_bedrock_runtime,smithy
Classifier: Development Status :: 2 - Pre-Alpha
Classifier: Intended Audience :: Developers
Classifier: Intended Audience :: System Administrators
Classifier: License :: OSI Approved :: Apache Software License
Classifier: Natural Language :: English
Classifier: Programming Language :: Python
Classifier: Programming Language :: Python :: 3
Classifier: Programming Language :: Python :: 3 :: Only
Classifier: Programming Language :: Python :: 3.12
Classifier: Programming Language :: Python :: 3.13
Requires-Python: >=3.12
Requires-Dist: smithy-aws-core[eventstream,json]~=0.1.0
Requires-Dist: smithy-core~=0.1.0
Requires-Dist: smithy-http[awscrt]~=0.1.0
